discord_components/__init__.py
discord_components/client.py
discord_components/component.py
discord_components/const.py
discord_components/dpy_overrides.py
discord_components/http.py
discord_components/interaction.py
discord_components/utils.py
discord_components/ext/filters.py
discord_components_xphnfix-1.0.0.dist-info/LICENSE
discord_components_xphnfix-1.0.0.dist-info/METADATA
discord_components_xphnfix-1.0.0.dist-info/WHEEL
discord_components_xphnfix-1.0.0.dist-info/top_level.txt
discord_components_xphnfix-1.0.0.dist-info/RECORD
