Metadata-Version: 2.1
Name: discord_components_xphnfix
Version: 1.0.0
Summary: Fork and Fix of/for discord_components, an unofficial library for discord components.
Home-page: https://debxylen.github.io/discord_components/
Author: Xylen
Author-email: priyanshudeb3@gmail.com
License: MIT License
Keywords: python,discord,discord.py,discord-components
Classifier: Intended Audience :: Developers
Classifier: License :: OSI Approved :: MIT License
Classifier: Natural Language :: English
Classifier: Operating System :: OS Independent
Classifier: Programming Language :: Python :: 3
Classifier: Programming Language :: Python :: 3.6
Classifier: Programming Language :: Python :: 3.7
Classifier: Programming Language :: Python :: 3.8
Classifier: Programming Language :: Python :: 3.9
Classifier: Topic :: Internet
Classifier: Topic :: Software Development :: Libraries :: Python Modules
Classifier: Topic :: Software Development :: Libraries
Classifier: Topic :: Utilities
Requires-Python: >=3.6
License-File: LICENSE
Requires-Dist: discord.py
Requires-Dist: aiohttp
